xmchat/__init__.py
xmchat/robot.py
xmchat-1.0.0.dist-info/LICENSE
xmchat-1.0.0.dist-info/METADATA
xmchat-1.0.0.dist-info/WHEEL
xmchat-1.0.0.dist-info/top_level.txt
xmchat-1.0.0.dist-info/RECORD
