Metadata-Version: 2.1
Name: xmchat
Version: 1.0.0
Summary: Library for building powerful interactive chatbot in Python
Home-page: https://github.com/haomingw/xmchat
Author: Haoming Wang
License: Apache 2.0
Platform: UNKNOWN
Classifier: Development Status :: 5 - Production/Stable
Classifier: Intended Audience :: Developers
Classifier: License :: OSI Approved :: Apache Software License
Classifier: Operating System :: OS Independent
Classifier: Programming Language :: Python :: 3
Classifier: Programming Language :: Python :: 3.6
Classifier: Programming Language :: Python :: 3.7
Classifier: Programming Language :: Python :: 3 :: Only
Classifier: Programming Language :: Python
Classifier: Topic :: Software Development
Requires-Python: >=3.6
